pyramid_mailgun/__init__.py
pyramid_mailgun-0.0.2.dist-info/DESCRIPTION.rst
pyramid_mailgun-0.0.2.dist-info/METADATA
pyramid_mailgun-0.0.2.dist-info/RECORD
pyramid_mailgun-0.0.2.dist-info/WHEEL
pyramid_mailgun-0.0.2.dist-info/metadata.json
pyramid_mailgun-0.0.2.dist-info/top_level.txt
