Metadata-Version: 2.0
Name: pyramid-mailgun
Version: 0.0.2
Summary: Mailgun integration for Pyramid framework
Home-page: https://github.com/evannook/pyramid_mailgun
Author: Evan Nook
Author-email: evan@innonook.com
License: MIT
Platform: UNKNOWN
Classifier: Development Status :: 5 - Production/Stable
Classifier: Programming Language :: Python :: 3.4
Classifier: Programming Language :: Python :: 3.5
Requires-Dist: requests
